ebal/__init__.py
ebal/binary.py
ebal/continuous.py
ebal-1.0.0.dist-info/licenses/LICENSE
ebal-1.0.0.dist-info/METADATA
ebal-1.0.0.dist-info/WHEEL
ebal-1.0.0.dist-info/top_level.txt
ebal-1.0.0.dist-info/RECORD
