Metadata-Version: 2.4
Name: ebal
Version: 1.0.0
Summary: Entropy Balancing for Causal Inference - Binary and Continuous Treatment
Author: Eddie Yang
License: MIT
Project-URL: Homepage, https://github.com/EddieYang211/ebal-py
Project-URL: Repository, https://github.com/EddieYang211/ebal-py.git
Project-URL: Issues, https://github.com/EddieYang211/ebal-py/issues
Keywords: entropy balancing,causal inference,propensity score,treatment effect,ATT,ATE,ATC,observational studies
Classifier: Development Status :: 4 - Beta
Classifier: Intended Audience :: Science/Research
Classifier: License :: OSI Approved :: MIT License
Classifier: Operating System :: OS Independent
Classifier: Programming Language :: Python :: 3
Classifier: Programming Language :: Python :: 3.8
Classifier: Programming Language :: Python :: 3.9
Classifier: Programming Language :: Python :: 3.10
Classifier: Programming Language :: Python :: 3.11
Classifier: Programming Language :: Python :: 3.12
Classifier: Topic :: Scientific/Engineering :: Mathematics
Requires-Python: >=3.8
License-File: LICENSE
Requires-Dist: numpy>=1.20.0
Requires-Dist: scipy>=1.6.0
Requires-Dist: scikit-learn>=0.24.0
Requires-Dist: statsmodels>=0.12.0
Requires-Dist: pandas>=1.2.0
Provides-Extra: dev
Requires-Dist: pytest>=7.0.0; extra == "dev"
Dynamic: license-file
